FSM.v
module FSM(input clk, input reset, input x, output reg z);

	reg [1:0] state, nextstate;
	parameter S0=0, S1=1 , S2=2 , S3=3;

	always @(posedge clk or posedge reset) // always block to update state
		if (reset)
			state <= S0;
		else
			state <= nextstate;
	always @(state) // always block to compute output
		begin
			case(state)
			S0: z <= 1;// for 0 at start 
			S1: z <= 0;
			S2: z<=0;
			S3: z<=1;// when the sequence reaches number of 1 divisible by 3
			endcase
		end
	always @(state or x) // always block to compute nextstate
		begin
		nextstate <= S0;
			case(state)
			S0: begin
				if(!x)
					nextstate<=S0;
				else
					nextstate<=S1;
				end
			S1: begin
				if(!x)
					nextstate <= S1;
				else
					nextstate<=S2;
				end
			S2:begin
				if(!x)
					nextstate<=S2;
				else
					nextstate<=S3;
				end
			S3: begin
				if(!x)
					nextstate<=S3;
				else
					nextstate<=S1;
				end
			endcase
		end
endmodule

Testbench_FSM.v
module Testbench_FSM();

	reg clk,reset,x;
	wire z;
	integer i;
	
	FSM f1(.*);// module instanciation and connection to testbench
	initial begin
		clk=0;reset=0;x=0;
#2 reset=1;// resetting
#4 reset=0;x=0;// inputs sequences
#4 x=0;
#4 x=1;
#4 x=0;
#4 x=1;
#4 x=1;
#4 x=1;
#4 x=0;
#4 x=1;
#4 x=1;
#4 x=1;
#4 x=0;
#4 x=1;
#10 x=0;
#4 $finish;
		
	end
	
	initial begin// variable dump fil creation for waveform viewing
		$dumpfile("dump.vcd");
		$dumpvars(1);
	end

	initial begin
		
		for(i = 0; i <= 62; i = i + 4) begin
			#i;
			$monitor("Time = %0t, x = %b, z = %b", $time, x, z);
		end
	end

	initial forever// clock generation
	
		#2 clk=~clk;

	
endmodule

dump.vcd
$date
	Tue Nov 28 16:10:53 2023
$end
$version
	ModelSim Version 2020.1
$end
$timescale
	1ps
$end

$scope module Testbench_FSM $end
$var reg 1 ! clk $end
$var reg 1 " reset $end
$var reg 1 # x $end
$var wire 1 $ z $end
$var integer 32 % i $end
$upscope $end
$enddefinitions $end
#0
$dumpvars
0!
0"
0#
b100 %
x$
$end
#2
1"
1!
1$
#4
b1000 %
0!
#6
0"
1!
#8
0!
#10
1!
#12
b1100 %
0!
#14
1#
1!
#16
0!
#18
0#
1!
0$
#20
0!
#22
1#
1!
#24
b10000 %
0!
#26
1!
#28
0!
#30
1!
1$
#32
0!
#34
0#
1!
0$
#36
0!
#38
1#
1!
#40
b10100 %
0!
#42
1!
#44
0!
#46
1!
1$
#48
0!
#50
0#
1!
0$
#52
0!
#54
1#
1!
#56
0!
#58
1!
#60
b11000 %
0!
#62
1!
1$
#64
0#
0!
