FSM.v
module FSM(input clk, input reset, input ins, output reg outs);

	reg [1:0] currState, nextState;
	parameter S0=0;
	parameter S1=1;
	parameter S2=2; 
	parameter S3=3;

	always @(posedge clk or posedge reset)
		if (reset)
			currState <= S0;
		else
			currState <= nextState;
	always @(currState) 
		begin
			case(currState)
			S0: outs <= 1;
			S1: outs <= 0;
			S2: outs <= 0;
			S3: outs <= 1;
			endcase
		end
	always @(currState or ins)
		begin
		nextState <= S0;
			case(currState)
			S0: begin
				if(!ins)
					nextState<=S0;
				else
					nextState<=S1;
				end
			S1: begin
				if(!ins)
					nextState <= S1;
				else
					nextState<=S2;
				end
			S2:begin
				if(!ins)
					nextState<=S2;
				else
					nextState<=S3;
				end
			S3: begin
				if(!ins)
					nextState<=S3;
				else
					nextState<=S1;
				end
			endcase
		end
endmodule

Testbench_FSM.v
module Testbench_FSM();

	reg clk,reset,x;
	wire z;
	integer i;
	
	FSM f1(.*);// module instanciation and connection to testbench
	initial begin
		clk=0;reset=0;x=0;
#2 reset=1;// resetting
#4 reset=0;x=0;// inputs sequences
#4 x=0;
#4 x=1;
#4 x=0;
#4 x=1;
#4 x=1;
#4 x=1;
#4 x=0;
#4 x=1;
#4 x=1;
#4 x=1;
#4 x=0;
#4 x=1;
#10 x=0;
#4 $finish;
		
	end
	
	initial begin// variable dump fil creation for waveform viewing
		$dumpfile("dump.vcd");
		$dumpvars(1);
	end

	initial begin
		
		for(i = 0; i <= 62; i = i + 4) begin
			#i;
			$monitor("Time = %0t, x = %b, z = %b", $time, x, z);
		end
	end

	initial forever// clock generation
	
		#2 clk=~clk;

	
endmodule

dsd_hw2/dump.vcd
$date
	Tue Nov 28 19:13:09 2023
$end
$version
	ModelSim Version 2020.1
$end
$timescale
	1ps
$end

$scope module Testbench_FSM $end
$var reg 1 ! clk $end
$var reg 1 " reset $end
$var reg 1 # x $end
$var wire 1 $ z $end
$var integer 32 % i $end
$upscope $end
$enddefinitions $end
#0
$dumpvars
0!
0"
0#
b100 %
x$
$end
#2
1"
1!
1$
#4
b1000 %
0!
#6
0"
1!
#8
0!
#10
1!
#12
b1100 %
0!
#14
1#
1!
#16
0!
#18
0#
1!
0$
#20
0!
#22
1#
1!
#24
b10000 %
0!
#26
1!
#28
0!
#30
1!
1$
#32
0!
#34
0#
1!
0$
#36
0!
#38
1#
1!
#40
b10100 %
0!
#42
1!
#44
0!
#46
1!
1$
#48
0!
#50
0#
1!
0$
#52
0!
#54
1#
1!
#56
0!
#58
1!
#60
b11000 %
0!
#62
1!
1$
#64
0#
0!
